MANIFEST.in
README
setup.py
arsdkxml/__init__.py
arsdkxml/arsdkgen.py
arsdkxml/arsdkparser.py
arsdkxml.egg-info/PKG-INFO
arsdkxml.egg-info/SOURCES.txt
arsdkxml.egg-info/dependency_links.txt
arsdkxml.egg-info/not-zip-safe
arsdkxml.egg-info/top_level.txt
arsdkxml/xml/ardrone3.xml
arsdkxml/xml/common.xml
arsdkxml/xml/controller_info.xml
arsdkxml/xml/debug.xml
arsdkxml/xml/drone_manager.xml
arsdkxml/xml/followme.xml
arsdkxml/xml/generic.xml
arsdkxml/xml/jpsumo.xml
arsdkxml/xml/mapper.xml
arsdkxml/xml/mapper_mini.xml
arsdkxml/xml/minidrone.xml
arsdkxml/xml/powerup.xml
arsdkxml/xml/rc.xml
arsdkxml/xml/skyctrl.xml
arsdkxml/xml/wifi.xml